mthpower_taal-0.9.0.dist-info/DESCRIPTION.rst
mthpower_taal-0.9.0.dist-info/METADATA
mthpower_taal-0.9.0.dist-info/RECORD
mthpower_taal-0.9.0.dist-info/WHEEL
mthpower_taal-0.9.0.dist-info/metadata.json
mthpower_taal-0.9.0.dist-info/top_level.txt
mthpower_taal-0.9.0.dist-info/zip-safe
taal/__init__.py
taal/constants.py
taal/exceptions.py
taal/models.py
taal/strategies.py
taal/translatablestring.py
taal/kaiso/__init__.py
taal/kaiso/context_managers.py
taal/kaiso/manager.py
taal/kaiso/types.py
taal/sqlalchemy/__init__.py
taal/sqlalchemy/events.py
taal/sqlalchemy/types.py
