Metadata-Version: 2.0
Name: mthpower-taal
Version: 0.9.0
Summary: Model translations
Home-page: https://github.com/mthpower/taal
Author: Matthew Power
Author-email: matthew@mthpower.uk
License: UNKNOWN
Platform: UNKNOWN
Classifier: Development Status :: 3 - Alpha
Classifier: Programming Language :: Python
Classifier: Intended Audience :: Developers
Classifier: Natural Language :: English
Classifier: Topic :: Software Development
Classifier: Topic :: Utilities
Requires-Dist: sqlalchemy (>=0.9)
